MANIFEST.in
README.md
setup.py
flask_debugtb_elasticsearch/__init__.py
flask_debugtb_elasticsearch/panel.py
flask_debugtb_elasticsearch/utils.py
flask_debugtb_elasticsearch/version.py
flask_debugtb_elasticsearch.egg-info/PKG-INFO
flask_debugtb_elasticsearch.egg-info/SOURCES.txt
flask_debugtb_elasticsearch.egg-info/dependency_links.txt
flask_debugtb_elasticsearch.egg-info/entry_points.txt
flask_debugtb_elasticsearch.egg-info/requires.txt
flask_debugtb_elasticsearch.egg-info/top_level.txt
flask_debugtb_elasticsearch/templates/elasticsearch.html