Metadata-Version: 1.1
Name: flask-debugtb-elasticsearch
Version: 0.1.4
Summary: Flask debug toolbar panel for elasticsearch queries.
Home-page: https://github.com/heynemann/flask-debugtb-elasticsearch
Author: Bernardo Heynemann
Author-email: heynemann@gmail.com
License: MIT
Keywords: flask elasticsearch debug toolbar
Platform: UNKNOWN
Classifier: Development Status :: 4 - Beta
Classifier: Intended Audience :: Developers
Classifier: License :: OSI Approved :: MIT License
Classifier: Natural Language :: English
Classifier: Operating System :: Unix
Classifier: Programming Language :: Python :: 2.7
Classifier: Programming Language :: Python :: 3.4
Classifier: Programming Language :: Python :: Implementation :: PyPy
Classifier: Operating System :: OS Independent
